mvector/__init__.py
mvector/predict.py
mvector/trainer.py
mvector/configs/augmentation.yml
mvector/configs/cam++.yml
mvector/configs/ecapa_tdnn.yml
mvector/configs/eres2net.yml
mvector/configs/res2net.yml
mvector/configs/resnet_se.yml
mvector/configs/tdnn.yml
mvector/data_utils/__init__.py
mvector/data_utils/collate_fn.py
mvector/data_utils/featurizer.py
mvector/data_utils/pk_sampler.py
mvector/data_utils/reader.py
mvector/infer_utils/__init__.py
mvector/infer_utils/player.py
mvector/infer_utils/speaker_diarization.py
mvector/infer_utils/viewer.py
mvector/loss/__init__.py
mvector/loss/aamloss.py
mvector/loss/amloss.py
mvector/loss/armloss.py
mvector/loss/celoss.py
mvector/loss/sphereface2.py
mvector/loss/subcenterloss.py
mvector/loss/tripletangularmarginloss.py
mvector/metric/__init__.py
mvector/metric/metrics.py
mvector/models/__init__.py
mvector/models/campplus.py
mvector/models/ecapa_tdnn.py
mvector/models/eres2net.py
mvector/models/fc.py
mvector/models/pooling.py
mvector/models/res2net.py
mvector/models/resnet_se.py
mvector/models/tdnn.py
mvector/models/utils.py
mvector/optimizer/__init__.py
mvector/optimizer/scheduler.py
mvector/utils/__init__.py
mvector/utils/checkpoint.py
mvector/utils/record.py
mvector/utils/utils.py
mvector-1.1.6.dist-info/LICENSE
mvector-1.1.6.dist-info/METADATA
mvector-1.1.6.dist-info/WHEEL
mvector-1.1.6.dist-info/top_level.txt
mvector-1.1.6.dist-info/RECORD
