Metadata-Version: 2.1
Name: mvector
Version: 1.1.6
Summary: Voice Print Recognition toolkit on Pytorch
Home-page: https://github.com/yeyupiaoling/VoiceprintRecognition_Pytorch
Download-URL: https://github.com/yeyupiaoling/VoiceprintRecognition_Pytorch.git
Author: yeyupiaoling
License: Apache License 2.0
Keywords: Voice,Pytorch
Classifier: Intended Audience :: Developers
Classifier: License :: OSI Approved :: Apache Software License
Classifier: Operating System :: OS Independent
Classifier: Natural Language :: Chinese (Simplified)
Classifier: Programming Language :: Python :: 3
Classifier: Programming Language :: Python :: 3.5
Classifier: Programming Language :: Python :: 3.6
Classifier: Programming Language :: Python :: 3.7
Classifier: Programming Language :: Python :: 3.8
Classifier: Programming Language :: Python :: 3.9
Classifier: Topic :: Utilities
License-File: LICENSE
Requires-Dist: numpy>=1.19.2
Requires-Dist: tqdm>=4.59.0
Requires-Dist: visualdl==2.5.3
Requires-Dist: resampy>=0.2.2
Requires-Dist: soundfile>=0.12.1
Requires-Dist: soundcard>=0.4.2
Requires-Dist: pyyaml>=5.4.1
Requires-Dist: scikit-learn>=1.5.2
Requires-Dist: pydub>=0.25.1
Requires-Dist: torchinfo>=1.7.2
Requires-Dist: loguru>=0.7.2
Requires-Dist: yeaudio>=0.0.7
